sgx/__init__.py
sgx/attestaion.py
sgx/client.py
sgx/ecdh_provider.py
sgx/keygen.py
sgx/session.py
sgx/wordlist.txt
sgx_storage_client-0.0.6.dist-info/METADATA
sgx_storage_client-0.0.6.dist-info/WHEEL
sgx_storage_client-0.0.6.dist-info/top_level.txt
sgx_storage_client-0.0.6.dist-info/RECORD
